{"id":20423462,"title":"tabiispor","upcoming":[{"title":"UEFA AVRUPA LİGİ FUTBOL KARŞILAŞMASI  BRANN - FENERBAHÇE ","start":"2025-12-26T22:20:00.000","end":"2025-12-27T00:05:00.000"},{"title":"ONSUZ ASLA","start":"2025-12-27T00:05:00.000","end":"2025-12-27T00:10:00.000"},{"title":"UEFA AVRUPA KONFERANS LİGİ FUTBOL KARŞILAŞMASI  SAMSUNSPOR - HAMRUN SPARTANS ","start":"2025-12-27T00:10:00.000","end":"2025-12-27T01:50:00.000"},{"title":"TRT SPOR YILDIZ ORTAK YAYIN","start":"2025-12-27T01:50:00.000","end":"2025-12-27T09:40:00.000"},{"title":"İTALYA SÜPER KUPA FİNAL  FUTBOL KARŞILAŞMASI  NAPOLI - BOLOGNA","start":"2025-12-27T09:30:00.000","end":"2025-12-27T11:15:00.000"},{"title":"UEFA ŞAMPİYONLAR LİGİ MAGAZİN","start":"2025-12-27T11:15:00.000","end":"2025-12-27T11:40:00.000"},{"title":"OYUN MODU","start":"2025-12-27T11:40:00.000","end":"2025-12-27T11:55:00.000"},{"title":"Almanak","start":"2025-12-27T11:55:00.000","end":"2025-12-27T12:00:00.000"},{"title":"AVRUPA SAHNESİ","start":"2025-12-27T12:00:00.000","end":"2025-12-27T13:30:00.000"},{"title":"UEFA ŞAMPİYONLAR LİGİ FUTBOL KARŞILAŞMASI  BARCELONA - E.FRANKFURT ","start":"2025-12-27T13:30:00.000","end":"2025-12-27T15:15:00.000"},{"title":"Almanak","start":"2025-12-27T15:15:00.000","end":"2025-12-27T15:30:00.000"},{"title":"İskoçya Premier Lig Futbol Karşılaşması \"Hibernian - Heart Of Midlothian\"","start":"2025-12-27T15:30:00.000","end":"2025-12-27T17:20:00.000"},{"title":"TÜM ZAMANLARIN EN İYİLERİ (THE GOAT)","start":"2025-12-27T17:20:00.000","end":"2025-12-27T17:50:00.000"},{"title":"Suudi Arabistan Pro Lig Futbol Karşılaşması \"Al Nassr - Al Okhdood\"","start":"2025-12-27T17:50:00.000","end":"2025-12-27T19:40:00.000"},{"title":"YENİLMEZLER","start":"2025-12-27T19:40:00.000","end":"2025-12-27T20:05:00.000"},{"title":"BİZİM LİGLER","start":"2025-12-27T20:05:00.000","end":"2025-12-27T20:30:00.000"},{"title":"Suudi Arabistan Pro Lig Futbol Karşılaşması \"Al Ittihad - Al Shabab\"","start":"2025-12-27T20:30:00.000","end":"2025-12-27T22:20:00.000"},{"title":"UEFA ŞAMPİYONLAR LİGİ FUTBOL KARŞILAŞMASI  JUVENTUS - PAFOS","start":"2025-12-27T22:20:00.000","end":"2025-12-28T00:00:00.000"},{"title":"UEFA AVRUPA KONFERANS LİGİ FUTBOL KARŞILAŞMASI  MAINZ - SAMSUNSPOR ","start":"2025-12-28T00:00:00.000","end":"2025-12-28T01:45:00.000"},{"title":"Almanak","start":"2025-12-28T01:45:00.000","end":"2025-12-28T01:50:00.000"},{"title":"TRT SPOR YILDIZ ORTAK YAYIN","start":"2025-12-28T01:50:00.000","end":"2025-12-28T09:30:00.000"},{"title":"UEFA AVRUPA LİGİ FUTBOL KARŞILAŞMASI  UTRECHT - NOTTINGHAM FOREST","start":"2025-12-28T09:30:00.000","end":"2025-12-28T11:10:00.000"},{"title":"Almanak","start":"2025-12-28T11:10:00.000","end":"2025-12-28T11:15:00.000"},{"title":"UEFA AVRUPA LİGİ FUTBOL KARŞILAŞMASI  DINAMO ZAGREB - REAL BETIS","start":"2025-12-28T11:15:00.000","end":"2025-12-28T12:55:00.000"},{"title":"Almanak","start":"2025-12-28T12:55:00.000","end":"2025-12-28T13:05:00.000"},{"title":"ONSUZ ASLA","start":"2025-12-28T13:05:00.000","end":"2025-12-28T13:10:00.000"},{"title":"UEFA AVRUPA LİGİ MAGAZİN","start":"2025-12-28T13:10:00.000","end":"2025-12-28T14:00:00.000"},{"title":"ŞAMPİYONLAR LİGİ ÖZETLER","start":"2025-12-28T14:00:00.000","end":"2025-12-28T15:25:00.000"},{"title":"Yapabilir Misin?","start":"2025-12-28T15:25:00.000","end":"2025-12-28T15:40:00.000"},{"title":"UEFA ŞAMPİYONLAR LİGİ MAGAZİN","start":"2025-12-28T15:40:00.000","end":"2025-12-28T16:05:00.000"},{"title":"UEFA AVRUPA LİGİ FUTBOL KARŞILAŞMASI  MIDTJYLLAND - GENK","start":"2025-12-28T16:05:00.000","end":"2025-12-28T17:45:00.000"},{"title":"Almanak","start":"2025-12-28T17:45:00.000","end":"2025-12-28T17:55:00.000"},{"title":"UEFA AVRUPA LİGİ FUTBOL KARŞILAŞMASI  CELTIC - ROMA","start":"2025-12-28T17:55:00.000","end":"2025-12-28T19:35:00.000"},{"title":"Almanak","start":"2025-12-28T19:35:00.000","end":"2025-12-28T19:45:00.000"},{"title":"UEFA AVRUPA LİGİ FUTBOL KARŞILAŞMASI  BRANN - FENERBAHÇE ","start":"2025-12-28T19:45:00.000","end":"2025-12-28T21:25:00.000"},{"title":"Almanak","start":"2025-12-28T21:25:00.000","end":"2025-12-28T21:35:00.000"},{"title":"UEFA ŞAMPİYONLAR LİGİ FUTBOL KARŞILAŞMASI  CLUB BRUGGE - ARSENAL","start":"2025-12-28T21:35:00.000","end":"2025-12-28T23:15:00.000"},{"title":"Almanak","start":"2025-12-28T23:15:00.000","end":"2025-12-28T23:25:00.000"},{"title":"UEFA ŞAMPİYONLAR LİGİ FUTBOL KARŞILAŞMASI  BAYERN MUNIH - SPORTING","start":"2025-12-28T23:25:00.000","end":"2025-12-29T01:05:00.000"},{"title":"Almanak","start":"2025-12-29T01:05:00.000","end":"2025-12-29T01:15:00.000"},{"title":"TÜM ZAMANLARIN EN İYİLERİ (THE GOAT)","start":"2025-12-29T01:15:00.000","end":"2025-12-29T01:40:00.000"},{"title":"Almanak","start":"2025-12-29T01:40:00.000","end":"2025-12-29T01:50:00.000"},{"title":"TRT SPOR YILDIZ ORTAK YAYIN","start":"2025-12-29T01:50:00.000","end":"2025-12-29T09:30:00.000"}]}