{"id":20423462,"title":"tabiispor","upcoming":[{"title":"UEFA AVRUPA KONFERANS LİGİ FUTBOL KARŞILAŞMASI  SAMSUNSPOR - HAMRUN SPARTANS ","start":"2025-11-09T00:00:00.000","end":"2025-11-09T01:40:00.000"},{"title":"ONSUZ ASLA","start":"2025-11-09T01:40:00.000","end":"2025-11-09T01:50:00.000"},{"title":"TRT SPOR YILDIZ ORTAK YAYIN","start":"2025-11-09T01:50:00.000","end":"2025-11-09T09:30:00.000"},{"title":"UEFA AVRUPA LİGİ ÖZETLER","start":"2025-11-09T09:30:00.000","end":"2025-11-09T10:10:00.000"},{"title":"UEFA ŞAMPİYONLAR LİGİ FUTBOL KARŞILAŞMASI  AJAX - GALATASARAY","start":"2025-11-09T10:10:00.000","end":"2025-11-09T11:50:00.000"},{"title":"UEFA KONFERANS LİGİ ÖZETLER","start":"2025-11-09T11:50:00.000","end":"2025-11-09T12:10:00.000"},{"title":"UEFA Avrupa Ligi Futbol Karşılaşması \"Kızılyıldız - Lille\"","start":"2025-11-09T12:10:00.000","end":"2025-11-09T13:50:00.000"},{"title":"ŞAMPİYONLAR LİGİ ÖZETLER","start":"2025-11-09T13:50:00.000","end":"2025-11-09T15:10:00.000"},{"title":" SPORUN İKONLARI","start":"2025-11-09T15:10:00.000","end":"2025-11-09T15:35:00.000"},{"title":"UEFA AVRUPA LİGİ FUTBOL KARŞILAŞMASI  STURM GRAZ - NOTTINGHAM FOREST","start":"2025-11-09T15:35:00.000","end":"2025-11-09T17:15:00.000"},{"title":"DEPLASMAN LEZZETLERİ","start":"2025-11-09T17:15:00.000","end":"2025-11-09T17:45:00.000"},{"title":"ONSUZ ASLA","start":"2025-11-09T17:45:00.000","end":"2025-11-09T18:00:00.000"},{"title":"İskoça Premier Lig Futbol Karşılaşması \"Dundee - Rangers\"","start":"2025-11-09T18:00:00.000","end":"2025-11-09T19:50:00.000"},{"title":"UEFA AVRUPA LİGİ MAGAZİN","start":"2025-11-09T19:50:00.000","end":"2025-11-09T20:40:00.000"},{"title":"UEFA Avrupa Ligi Futbol Karşılaşması \"Basel - FCSB\"","start":"2025-11-09T20:40:00.000","end":"2025-11-09T22:20:00.000"},{"title":"UEFA Avrupa Ligi Futbol Karşılaşması \"Nice - Freiburg\"","start":"2025-11-09T22:20:00.000","end":"2025-11-10T00:00:00.000"},{"title":"UEFA AVRUPA LİGİ FUTBOL KARŞILAŞMASI  VIKTORIA PLZEN - FENERBAHÇE ","start":"2025-11-10T00:00:00.000","end":"2025-11-10T01:40:00.000"},{"title":"TRT SPOR YILDIZ ORTAK YAYIN","start":"2025-11-10T01:40:00.000","end":"2025-11-10T09:30:00.000"}]}