{"id":129459,"title":"trt2","upcoming":[{"title":"Edebiyat Dünyası","start":"2025-05-07T08:30:00.000","end":"2025-05-07T09:30:00.000"},{"title":"İşaretler","start":"2025-05-07T09:30:00.000","end":"2025-05-07T10:00:00.000"},{"title":"Selçuklu Mirası","start":"2025-05-07T10:00:00.000","end":"2025-05-07T10:30:00.000"},{"title":"Karalama Defteri ","start":"2025-05-07T10:30:00.000","end":"2025-05-07T11:00:00.000"},{"title":"İstisnai Renkler","start":"2025-05-07T11:00:00.000","end":"2025-05-07T11:30:00.000"},{"title":"Sinematograf","start":"2025-05-07T11:30:00.000","end":"2025-05-07T12:00:00.000"},{"title":"Hayat Sanat","start":"2025-05-07T12:00:00.000","end":"2025-05-07T12:30:00.000"},{"title":"Tarih Söyleşileri","start":"2025-05-07T12:30:00.000","end":"2025-05-07T13:30:00.000"},{"title":"Konsere Davet","start":"2025-05-07T13:30:00.000","end":"2025-05-07T13:45:00.000"},{"title":"Belgesel: Gazze'yi Görüyorum","start":"2025-05-07T13:45:00.000","end":"2025-05-07T14:20:00.000"},{"title":"Uluslararası İslam Sanatları Fuarı","start":"2025-05-07T14:20:00.000","end":"2025-05-07T15:00:00.000"},{"title":"Yabancı Sinema: Sınıf (The Class)","start":"2025-05-07T15:00:00.000","end":"2025-05-07T17:15:00.000"},{"title":"Keşif","start":"2025-05-07T17:15:00.000","end":"2025-05-07T17:30:00.000"},{"title":"Cumhuriyetin Mimari Eserleri","start":"2025-05-07T17:30:00.000","end":"2025-05-07T18:00:00.000"},{"title":"Hayat Sanat","start":"2025-05-07T18:00:00.000","end":"2025-05-07T18:30:00.000"},{"title":"Espas","start":"2025-05-07T18:30:00.000","end":"2025-05-07T19:00:00.000"},{"title":"Eve Dönen Miras","start":"2025-05-07T19:00:00.000","end":"2025-05-07T19:30:00.000"},{"title":"Bakış Boşluğu","start":"2025-05-07T19:30:00.000","end":"2025-05-07T20:15:00.000"},{"title":"Fotoğraflar","start":"2025-05-07T20:15:00.000","end":"2025-05-07T20:30:00.000"},{"title":"Tiyatrovizyon","start":"2025-05-07T20:30:00.000","end":"2025-05-07T21:00:00.000"},{"title":"Sanatçının Şehri","start":"2025-05-07T21:00:00.000","end":"2025-05-07T21:30:00.000"},{"title":"Yabancı Sinema: Elveda Gülsarı (Goodbye, Gulsary!)","start":"2025-05-07T21:30:00.000","end":"2025-05-07T23:15:00.000"},{"title":"Medeniyet Ve Mimari","start":"2025-05-07T23:15:00.000","end":"2025-05-07T23:45:00.000"},{"title":"Geri Dönüşen Sanat","start":"2025-05-07T23:45:00.000","end":"2025-05-08T00:00:00.000"},{"title":"Tiyatrovizyon","start":"2025-05-08T00:00:00.000","end":"2025-05-08T00:30:00.000"},{"title":"Sanatçının Şehri","start":"2025-05-08T00:30:00.000","end":"2025-05-08T01:00:00.000"},{"title":"Yabancı Sinema: Elveda Gülsarı (Goodbye, Gulsary!)","start":"2025-05-08T01:00:00.000","end":"2025-05-08T02:45:00.000"},{"title":"Bakış Boşluğu","start":"2025-05-08T02:45:00.000","end":"2025-05-08T03:30:00.000"},{"title":"Coğrafyadan Kültüre Bağ","start":"2025-05-08T03:30:00.000","end":"2025-05-08T04:00:00.000"},{"title":"Sarayın Lezzetleri","start":"2025-05-08T04:00:00.000","end":"2025-05-08T04:30:00.000"},{"title":"Eve Dönen Miras","start":"2025-05-08T04:30:00.000","end":"2025-05-08T05:00:00.000"},{"title":"İstiklal Marşı","start":"2025-05-08T04:58:00.000","end":"2025-05-08T05:00:00.000"},{"title":"Resme Yolculuk","start":"2025-05-08T05:00:00.000","end":"2025-05-08T05:30:00.000"},{"title":"Musikişinas","start":"2025-05-08T05:30:00.000","end":"2025-05-08T06:00:00.000"},{"title":"Düğüm","start":"2025-05-08T06:00:00.000","end":"2025-05-08T06:30:00.000"},{"title":"Belgesel: Usta Eller (The Intelligent Hand)","start":"2025-05-08T06:30:00.000","end":"2025-05-08T07:15:00.000"},{"title":"Sûret","start":"2025-05-08T07:15:00.000","end":"2025-05-08T07:30:00.000"},{"title":"Hayat Sanat","start":"2025-05-08T07:30:00.000","end":"2025-05-08T08:00:00.000"},{"title":"Belgesel: Gazze'yi Görüyorum","start":"2025-05-08T08:00:00.000","end":"2025-05-08T08:30:00.000"},{"title":"Hülya Koçyiğit İle Film Gibi Hayatlar","start":"2025-05-08T08:30:00.000","end":"2025-05-08T09:30:00.000"},{"title":"Hafir","start":"2025-05-08T09:30:00.000","end":"2025-05-08T10:00:00.000"},{"title":"Bakış Boşluğu","start":"2025-05-08T10:00:00.000","end":"2025-05-08T10:45:00.000"},{"title":"Fotoğrafçının Kitabı","start":"2025-05-08T10:45:00.000","end":"2025-05-08T11:00:00.000"},{"title":"Cumhuriyetin Mimari Eserleri","start":"2025-05-08T11:00:00.000","end":"2025-05-08T11:30:00.000"},{"title":"Sanatçının Şehri","start":"2025-05-08T11:30:00.000","end":"2025-05-08T12:00:00.000"},{"title":"Hayat Sanat","start":"2025-05-08T12:00:00.000","end":"2025-05-08T12:30:00.000"},{"title":"Satranç Dünyası","start":"2025-05-08T12:30:00.000","end":"2025-05-08T13:00:00.000"},{"title":"Tiyatrovizyon","start":"2025-05-08T13:00:00.000","end":"2025-05-08T13:30:00.000"},{"title":"Eve Dönen Miras","start":"2025-05-08T13:30:00.000","end":"2025-05-08T14:00:00.000"},{"title":"Sinematograf","start":"2025-05-08T14:00:00.000","end":"2025-05-08T14:30:00.000"},{"title":"Espas","start":"2025-05-08T14:30:00.000","end":"2025-05-08T15:00:00.000"},{"title":"Yabancı Sinema: Elveda Gülsarı (Goodbye, Gulsary!)","start":"2025-05-08T15:00:00.000","end":"2025-05-08T16:45:00.000"},{"title":"Sanat Terimleri","start":"2025-05-08T16:45:00.000","end":"2025-05-08T17:00:00.000"},{"title":"Evliya Çelebi","start":"2025-05-08T17:00:00.000","end":"2025-05-08T18:00:00.000"},{"title":"Hayat Sanat","start":"2025-05-08T18:00:00.000","end":"2025-05-08T18:30:00.000"},{"title":"Medeniyet Ve Mimari","start":"2025-05-08T18:30:00.000","end":"2025-05-08T19:00:00.000"},{"title":"Resme Yolculuk","start":"2025-05-08T19:00:00.000","end":"2025-05-08T19:30:00.000"},{"title":"Sinema +","start":"2025-05-08T19:30:00.000","end":"2025-05-08T20:30:00.000"},{"title":"Edebî Sofralar","start":"2025-05-08T20:30:00.000","end":"2025-05-08T21:00:00.000"},{"title":"Kim Korkar Geleneksel Sanattan","start":"2025-05-08T21:00:00.000","end":"2025-05-08T21:30:00.000"},{"title":"Yabancı Sinema: Kurak Mevsim (Dry Season)","start":"2025-05-08T21:30:00.000","end":"2025-05-08T23:15:00.000"},{"title":"Felsefenin Serüveni","start":"2025-05-08T23:15:00.000","end":"2025-05-09T00:00:00.000"},{"title":"Belgesel: Usta Eller (The Intelligent Hand)","start":"2025-05-09T00:00:00.000","end":"2025-05-09T00:45:00.000"},{"title":"Destansı Kareler","start":"2025-05-09T00:45:00.000","end":"2025-05-09T01:00:00.000"},{"title":"Yabancı Sinema: Kurak Mevsim (Dry Season)","start":"2025-05-09T01:00:00.000","end":"2025-05-09T02:45:00.000"},{"title":"Yabancı Sinema: Yaşama Hevesi (Longing For The World)","start":"2025-05-09T02:45:00.000","end":"2025-05-09T04:00:00.000"},{"title":"Sinema +","start":"2025-05-09T04:00:00.000","end":"2025-05-09T05:00:00.000"},{"title":"İstiklal Marşı","start":"2025-05-09T04:58:00.000","end":"2025-05-09T05:00:00.000"},{"title":"Kim Korkar Geleneksel Sanattan","start":"2025-05-09T05:00:00.000","end":"2025-05-09T05:30:00.000"},{"title":"Felsefenin Serüveni","start":"2025-05-09T05:30:00.000","end":"2025-05-09T06:15:00.000"},{"title":"Fotoğraflar","start":"2025-05-09T06:15:00.000","end":"2025-05-09T06:30:00.000"},{"title":"İşaretler","start":"2025-05-09T06:30:00.000","end":"2025-05-09T07:00:00.000"},{"title":"Kadim Tasarımlar Ülkesi","start":"2025-05-09T07:00:00.000","end":"2025-05-09T07:30:00.000"},{"title":"Hayat Sanat","start":"2025-05-09T07:30:00.000","end":"2025-05-09T08:00:00.000"},{"title":"Sinematograf","start":"2025-05-09T08:00:00.000","end":"2025-05-09T08:30:00.000"},{"title":"Evliya Çelebi","start":"2025-05-09T08:30:00.000","end":"2025-05-09T09:30:00.000"},{"title":"Medeniyet Ve Mimari","start":"2025-05-09T09:30:00.000","end":"2025-05-09T10:00:00.000"},{"title":"Kim Korkar Geleneksel Sanattan","start":"2025-05-09T10:00:00.000","end":"2025-05-09T10:30:00.000"},{"title":"Sinema +","start":"2025-05-09T10:30:00.000","end":"2025-05-09T11:30:00.000"},{"title":"Kadim Tasarımlar Ülkesi","start":"2025-05-09T11:30:00.000","end":"2025-05-09T12:00:00.000"},{"title":"Hayat Sanat","start":"2025-05-09T12:00:00.000","end":"2025-05-09T12:30:00.000"},{"title":"Felsefenin Serüveni","start":"2025-05-09T12:30:00.000","end":"2025-05-09T13:15:00.000"},{"title":"Sanat Terimleri","start":"2025-05-09T13:15:00.000","end":"2025-05-09T13:30:00.000"},{"title":"Resme Yolculuk","start":"2025-05-09T13:30:00.000","end":"2025-05-09T14:00:00.000"},{"title":"Hafir","start":"2025-05-09T14:00:00.000","end":"2025-05-09T14:30:00.000"},{"title":"Düğüm","start":"2025-05-09T14:30:00.000","end":"2025-05-09T15:00:00.000"},{"title":"Yabancı Sinema: Kurak Mevsim (Dry Season)","start":"2025-05-09T15:00:00.000","end":"2025-05-09T16:45:00.000"},{"title":"Konsere Davet","start":"2025-05-09T16:45:00.000","end":"2025-05-09T17:00:00.000"},{"title":"İpek'çe Sohbetler","start":"2025-05-09T17:00:00.000","end":"2025-05-09T18:00:00.000"},{"title":"Hayat Sanat","start":"2025-05-09T18:00:00.000","end":"2025-05-09T18:30:00.000"},{"title":"İşaretler","start":"2025-05-09T18:30:00.000","end":"2025-05-09T19:00:00.000"},{"title":"Karalama Defteri ","start":"2025-05-09T19:00:00.000","end":"2025-05-09T19:15:00.000"},{"title":"Türkiye'yi Düşünmek","start":"2025-05-09T19:15:00.000","end":"2025-05-09T20:00:00.000"},{"title":"Belgesel: Fanny: Diğer Mendelssohn (Fanny: The Other Mendelssohn)","start":"2025-05-09T20:00:00.000","end":"2025-05-09T21:30:00.000"},{"title":"Yabancı Sinema: Yerdeniz Öyküleri (Tales From Earthsea)","start":"2025-05-09T21:30:00.000","end":"2025-05-09T23:30:00.000"},{"title":"Nazar İle Manzara","start":"2025-05-09T23:30:00.000","end":"2025-05-10T00:30:00.000"},{"title":"Agents Are Forever","start":"2025-05-10T00:30:00.000","end":"2025-05-10T02:00:00.000"},{"title":"Yabancı Sinema: Yerdeniz Öyküleri (Tales From Earthsea)","start":"2025-05-10T02:00:00.000","end":"2025-05-10T04:00:00.000"},{"title":"Türkiye'yi Düşünmek","start":"2025-05-10T04:00:00.000","end":"2025-05-10T04:45:00.000"},{"title":"Geri Dönüşen Sanat","start":"2025-05-10T04:45:00.000","end":"2025-05-10T05:00:00.000"},{"title":"İstiklal Marşı","start":"2025-05-10T04:58:00.000","end":"2025-05-10T05:00:00.000"},{"title":"Nazar İle Manzara","start":"2025-05-10T05:00:00.000","end":"2025-05-10T06:00:00.000"},{"title":"Fotoğrafçının Kitabı","start":"2025-05-10T06:00:00.000","end":"2025-05-10T06:15:00.000"},{"title":"Türkiye Atlası ","start":"2025-05-10T06:15:00.000","end":"2025-05-10T06:30:00.000"},{"title":"Edebî Sofralar","start":"2025-05-10T06:30:00.000","end":"2025-05-10T07:00:00.000"},{"title":"Satranç Dünyası","start":"2025-05-10T07:00:00.000","end":"2025-05-10T07:30:00.000"},{"title":"Hayat Sanat - Kolaj","start":"2025-05-10T07:30:00.000","end":"2025-05-10T08:00:00.000"},{"title":"İstisnai Renkler","start":"2025-05-10T08:00:00.000","end":"2025-05-10T08:30:00.000"},{"title":"Tiyatrovizyon","start":"2025-05-10T08:30:00.000","end":"2025-05-10T09:00:00.000"},{"title":"Karalama Defteri ","start":"2025-05-10T09:00:00.000","end":"2025-05-10T09:15:00.000"},{"title":"Sessizce","start":"2025-05-10T09:15:00.000","end":"2025-05-10T09:30:00.000"},{"title":"Cumhuriyetin Mimari Eserleri","start":"2025-05-10T09:30:00.000","end":"2025-05-10T10:00:00.000"},{"title":"Yabancı Sinema: X + Y","start":"2025-05-10T10:00:00.000","end":"2025-05-10T12:00:00.000"},{"title":"İpek'çe Sohbetler","start":"2025-05-10T12:00:00.000","end":"2025-05-10T13:00:00.000"},{"title":"Espas","start":"2025-05-10T13:00:00.000","end":"2025-05-10T13:30:00.000"},{"title":"Belgesel: Fanny: Diğer Mendelssohn (Fanny: The Other Mendelssohn)","start":"2025-05-10T13:30:00.000","end":"2025-05-10T15:00:00.000"},{"title":"Yabancı Sinema: Aşkın Gözü (Radiance)","start":"2025-05-10T15:00:00.000","end":"2025-05-10T16:45:00.000"},{"title":"Agents Are Forever","start":"2025-05-10T16:45:00.000","end":"2025-05-10T18:15:00.000"},{"title":"Sinema +","start":"2025-05-10T18:15:00.000","end":"2025-05-10T19:15:00.000"},{"title":"Kim Korkar Geleneksel Sanattan","start":"2025-05-10T19:15:00.000","end":"2025-05-10T19:45:00.000"},{"title":"Londra Senfoni Orkestrası Mahler ve Messiaen (LSO: Barbara Hannigan Conducts Mahler & Messiaen) ","start":"2025-05-10T19:45:00.000","end":"2025-05-10T21:30:00.000"},{"title":"Yabancı Sinema: Boş Ağlar (Empty Nets)","start":"2025-05-10T21:30:00.000","end":"2025-05-10T23:15:00.000"},{"title":"Londra Senfoni Orkestrası Mahler ve Messiaen (LSO: Barbara Hannigan Conducts Mahler & Messiaen) ","start":"2025-05-10T23:15:00.000","end":"2025-05-11T00:45:00.000"},{"title":"Yabancı Sinema: Boş Ağlar (Empty Nets)","start":"2025-05-11T00:45:00.000","end":"2025-05-11T02:30:00.000"},{"title":"Yabancı Sinema: Aşkın Gözü (Radiance)","start":"2025-05-11T02:30:00.000","end":"2025-05-11T04:15:00.000"},{"title":"Keşif","start":"2025-05-11T04:15:00.000","end":"2025-05-11T04:30:00.000"},{"title":"İpek'çe Sohbetler","start":"2025-05-11T04:30:00.000","end":"2025-05-11T05:30:00.000"},{"title":"İstiklal Marşı","start":"2025-05-11T05:28:00.000","end":"2025-05-11T05:30:00.000"},{"title":"Yabancı Sinema: X + Y","start":"2025-05-11T05:30:00.000","end":"2025-05-11T07:30:00.000"},{"title":"Hayat Sanat - Kolaj","start":"2025-05-11T07:30:00.000","end":"2025-05-11T08:00:00.000"},{"title":"Sanatı İzlemek","start":"2025-05-11T08:00:00.000","end":"2025-05-11T08:30:00.000"},{"title":"Düğüm","start":"2025-05-11T08:30:00.000","end":"2025-05-11T09:00:00.000"},{"title":"Edebî Sofralar","start":"2025-05-11T09:00:00.000","end":"2025-05-11T09:30:00.000"},{"title":"Kim Korkar Geleneksel Sanattan","start":"2025-05-11T09:30:00.000","end":"2025-05-11T10:00:00.000"},{"title":"Western: Kordura Kahramanları (They Came To Cordura)","start":"2025-05-11T10:00:00.000","end":"2025-05-11T12:00:00.000"},{"title":"Hülya Koçyiğit İle Film Gibi Hayatlar","start":"2025-05-11T12:00:00.000","end":"2025-05-11T13:00:00.000"},{"title":"İşaretler","start":"2025-05-11T13:00:00.000","end":"2025-05-11T13:30:00.000"},{"title":"Konsere Davet","start":"2025-05-11T13:30:00.000","end":"2025-05-11T13:45:00.000"},{"title":"Pazar Konseri","start":"2025-05-11T13:45:00.000","end":"2025-05-11T15:00:00.000"},{"title":"Yabancı Sinema: Ninni (Lullaby)","start":"2025-05-11T15:00:00.000","end":"2025-05-11T16:45:00.000"},{"title":"Tiyatrovizyon","start":"2025-05-11T16:45:00.000","end":"2025-05-11T17:15:00.000"},{"title":"Espas","start":"2025-05-11T17:15:00.000","end":"2025-05-11T17:45:00.000"},{"title":"Kadim Tasarımlar Ülkesi","start":"2025-05-11T17:45:00.000","end":"2025-05-11T18:15:00.000"},{"title":"Sanatçının Şehri","start":"2025-05-11T18:15:00.000","end":"2025-05-11T18:45:00.000"},{"title":"Cumhuriyetin Mimari Eserleri","start":"2025-05-11T18:45:00.000","end":"2025-05-11T19:15:00.000"},{"title":"Evliya Çelebi","start":"2025-05-11T19:15:00.000","end":"2025-05-11T20:00:00.000"},{"title":"Tiyatro Zamanı","start":"2025-05-11T20:00:00.000","end":"2025-05-11T21:30:00.000"},{"title":"Yabancı Sinema: Anneye Giden Yol (The Road To Mother)","start":"2025-05-11T21:30:00.000","end":"2025-05-11T23:45:00.000"},{"title":"Western: Kordura Kahramanları (They Came To Cordura)","start":"2025-05-11T23:45:00.000","end":"2025-05-12T01:45:00.000"},{"title":"Yabancı Sinema: Anneye Giden Yol (The Road To Mother)","start":"2025-05-12T01:45:00.000","end":"2025-05-12T04:00:00.000"},{"title":"Hülya Koçyiğit İle Film Gibi Hayatlar","start":"2025-05-12T04:00:00.000","end":"2025-05-12T05:00:00.000"}]}