{"id":129464,"title":"trtsporyildiz","upcoming":[{"title":"ULTRA ","start":"2026-03-28T09:45:00.000","end":"2026-03-28T10:00:00.000"},{"title":"Haber Bülteni","start":"2026-03-28T10:00:00.000","end":"2026-03-28T10:15:00.000"},{"title":"Olimpiyat Yıldızları","start":"2026-03-28T10:15:00.000","end":"2026-03-28T10:30:00.000"},{"title":"Süper Spor","start":"2026-03-28T10:30:00.000","end":"2026-03-28T11:00:00.000"},{"title":"41. DAKİKA","start":"2026-03-28T11:00:00.000","end":"2026-03-28T11:35:00.000"},{"title":"YILDIZ'DA SÖYLEŞİ","start":"2026-03-28T11:35:00.000","end":"2026-03-28T11:55:00.000"},{"title":"ARABICA COFFEE HOUSE VOLEYBOL KADINLAR 1. LİG YARI FİNAL ETABI İBA Kimya TED Ankara Kolejliler - Denizli B.Şehir Bld.","start":"2026-03-28T11:55:00.000","end":"2026-03-28T14:00:00.000"},{"title":"TEKERLEKLİ SANDALYE BASKETBOL / BAĞCILAR BELEDİYE ENG. SK-TSK REHBERLİK MERKEZİ","start":"2026-03-28T14:00:00.000","end":"2026-03-28T15:50:00.000"},{"title":"Süper Spor","start":"2026-03-28T15:50:00.000","end":"2026-03-28T16:20:00.000"},{"title":"ONSUZ ASLA","start":"2026-03-28T16:20:00.000","end":"2026-03-28T16:25:00.000"},{"title":"ARABICA COFFEE HOUSE VOLEYBOL KADINLAR 1. LİG YARI FİNAL ETABI Çanakkale Bld. - PTT","start":"2026-03-28T16:25:00.000","end":"2026-03-28T18:30:00.000"},{"title":"Olimpiyat Yıldızları","start":"2026-03-28T18:30:00.000","end":"2026-03-28T18:45:00.000"},{"title":"EUROLEAGUE ÖZETLER","start":"2026-03-28T18:45:00.000","end":"2026-03-28T19:05:00.000"},{"title":" GEREDE KIŞ TRİATLONU 2026 (ÖZEL DOSYA)","start":"2026-03-28T19:05:00.000","end":"2026-03-28T19:20:00.000"},{"title":"Nedir, Nasıl Oynanır?","start":"2026-03-28T19:20:00.000","end":"2026-03-28T19:25:00.000"},{"title":"HENTBOL EHF AVRUPA KUPASI ÇEYREK FİNALİ PAOK-BURSA BÜYÜKŞEHİR BSK","start":"2026-03-28T19:25:00.000","end":"2026-03-28T21:10:00.000"},{"title":"AVRUPA BİLARDO ŞAMPİYONASI-ÖZEL DOSYA","start":"2026-03-28T21:10:00.000","end":"2026-03-28T21:20:00.000"},{"title":"41. DAKİKA","start":"2026-03-28T21:20:00.000","end":"2026-03-28T21:55:00.000"},{"title":"OYUN MODU","start":"2026-03-28T21:55:00.000","end":"2026-03-28T22:10:00.000"},{"title":"4. Gün / 2. Bölüm ISU Artistik Buz Pateni Dünya Şampiyonası 2026","start":"2026-03-28T22:10:00.000","end":"2026-03-28T23:55:00.000"},{"title":"Süper Spor","start":"2026-03-28T23:55:00.000","end":"2026-03-29T00:25:00.000"},{"title":"Nedir, Nasıl Oynanır?","start":"2026-03-29T00:25:00.000","end":"2026-03-29T00:30:00.000"},{"title":"Haber Bülteni","start":"2026-03-29T00:30:00.000","end":"2026-03-29T00:45:00.000"},{"title":" GEREDE KIŞ TRİATLONU 2026 (ÖZEL DOSYA)","start":"2026-03-29T00:45:00.000","end":"2026-03-29T01:00:00.000"},{"title":"ALBÜMDEKİ YILDIZLAR","start":"2026-03-29T01:00:00.000","end":"2026-03-29T01:20:00.000"},{"title":"SORMAZSAM OLMAZ","start":"2026-03-29T01:20:00.000","end":"2026-03-29T01:35:00.000"},{"title":"BUZ HOKEYİ ERKEKLER SÜPER LİGİ PLAY-OFF FİNAL 1. MAÇ ","start":"2026-03-29T01:35:00.000","end":"2026-03-29T04:00:00.000"},{"title":"SATRANÇ DÜNYASI ","start":"2026-03-29T04:00:00.000","end":"2026-03-29T04:25:00.000"},{"title":"DREAM TEAMS","start":"2026-03-29T04:25:00.000","end":"2026-03-29T04:50:00.000"},{"title":"ETNOSPOR","start":"2026-03-29T04:50:00.000","end":"2026-03-29T05:10:00.000"},{"title":"SESSİZ OYUN DEFALYMPICS","start":"2026-03-29T05:10:00.000","end":"2026-03-29T05:45:00.000"},{"title":"YILDIZ'DA SÖYLEŞİ","start":"2026-03-29T05:45:00.000","end":"2026-03-29T06:05:00.000"},{"title":"ALBÜMDEKİ YILDIZLAR","start":"2026-03-29T06:05:00.000","end":"2026-03-29T06:25:00.000"},{"title":"KARDEŞLER TAKIMI","start":"2026-03-29T06:25:00.000","end":"2026-03-29T06:58:00.000"},{"title":"İstiklal Marşı","start":"2026-03-29T06:58:00.000","end":"2026-03-29T07:00:00.000"},{"title":"Haber Bülteni","start":"2026-03-29T07:00:00.000","end":"2026-03-29T07:15:00.000"},{"title":"OYUN MODU","start":"2026-03-29T07:15:00.000","end":"2026-03-29T07:30:00.000"},{"title":"Nedir, Nasıl Oynanır?","start":"2026-03-29T07:30:00.000","end":"2026-03-29T07:35:00.000"},{"title":"ALBÜMDEKİ YILDIZLAR","start":"2026-03-29T07:35:00.000","end":"2026-03-29T07:55:00.000"},{"title":"SORMAZSAM OLMAZ","start":"2026-03-29T07:55:00.000","end":"2026-03-29T08:10:00.000"},{"title":"EUROLEAGUE ÖZETLER","start":"2026-03-29T08:10:00.000","end":"2026-03-29T08:30:00.000"},{"title":"Haber Bülteni","start":"2026-03-29T08:30:00.000","end":"2026-03-29T08:45:00.000"},{"title":"ULTRA ","start":"2026-03-29T08:45:00.000","end":"2026-03-29T09:00:00.000"},{"title":"PEDALIN SENFONİSİ","start":"2026-03-29T09:00:00.000","end":"2026-03-29T09:25:00.000"},{"title":"SKI CLASSICS","start":"2026-03-29T09:25:00.000","end":"2026-03-29T12:00:00.000"},{"title":"AMPUTE FUTBOL / İZMİR BŞB SK- SGK KURUMSAL DANIŞMANLIK ŞİŞLİ YEDİTEPE ENG. SK ","start":"2026-03-29T12:00:00.000","end":"2026-03-29T13:10:00.000"},{"title":" GEREDE KIŞ TRİATLONU 2026 (ÖZEL DOSYA)","start":"2026-03-29T13:10:00.000","end":"2026-03-29T13:25:00.000"},{"title":"FIVB KAR VOLEYBOLU DÜNYA TURU ULUDAĞ ERKEKLER 3.'LÜK MAÇI","start":"2026-03-29T13:25:00.000","end":"2026-03-29T14:10:00.000"},{"title":"OYUN MODU","start":"2026-03-29T14:10:00.000","end":"2026-03-29T14:25:00.000"},{"title":"FIVB KAR VOLEYBOLU DÜNYA TURU ULUDAĞ KADINLAR 3.'LÜK MAÇI","start":"2026-03-29T14:25:00.000","end":"2026-03-29T15:10:00.000"},{"title":"Olimpiyat Yıldızları","start":"2026-03-29T15:10:00.000","end":"2026-03-29T15:25:00.000"},{"title":"FIVB KAR VOLEYBOLU DÜNYA TURU ULUDAĞ KADINLAR FİNAL MAÇI","start":"2026-03-29T15:25:00.000","end":"2026-03-29T16:10:00.000"},{"title":"SORMAZSAM OLMAZ","start":"2026-03-29T16:10:00.000","end":"2026-03-29T16:25:00.000"},{"title":"FIVB KAR VOLEYBOLU DÜNYA TURU ULUDAĞ ERKEKLER FİNAL MAÇI","start":"2026-03-29T16:25:00.000","end":"2026-03-29T17:10:00.000"},{"title":"ULTRA ","start":"2026-03-29T17:10:00.000","end":"2026-03-29T17:25:00.000"},{"title":"Nedir, Nasıl Oynanır?","start":"2026-03-29T17:25:00.000","end":"2026-03-29T17:30:00.000"},{"title":"Haber Bülteni","start":"2026-03-29T17:30:00.000","end":"2026-03-29T17:45:00.000"},{"title":"AVRUPA BİLARDO ŞAMPİYONASI-ÖZEL DOSYA","start":"2026-03-29T17:45:00.000","end":"2026-03-29T17:55:00.000"},{"title":"2025-2026 SEZONU VODAFONE SULTANLAR LİGİ / PLAY-OFF 5-8 ARAS KARGO-NİLÜFER BELEDİYESPOR EKER 1. MAÇ ","start":"2026-03-29T17:55:00.000","end":"2026-03-29T20:00:00.000"},{"title":"PEDALIN SENFONİSİ","start":"2026-03-29T20:00:00.000","end":"2026-03-29T20:25:00.000"},{"title":"BUZ HOKEYİ ERKEKLER SÜPER LİGİ PLAY-OFF FİNAL 2. MAÇ BUZADAM-ZEYTİNBURNU BSK","start":"2026-03-29T20:25:00.000","end":"2026-03-29T23:00:00.000"},{"title":"41. DAKİKA","start":"2026-03-29T23:00:00.000","end":"2026-03-29T23:45:00.000"},{"title":"ULTRA ","start":"2026-03-29T23:45:00.000","end":"2026-03-30T00:00:00.000"},{"title":"Haber Bülteni","start":"2026-03-30T00:00:00.000","end":"2026-03-30T00:15:00.000"},{"title":"2025-2026 SEZONU VODAFONE SULTANLAR LİGİ / PLAY-OFF 5-8 TÜRK HAVA YOLLARI-GALATASARAY DAIKIN 1. MAÇ ","start":"2026-03-30T00:15:00.000","end":"2026-03-30T02:20:00.000"},{"title":"SKI CLASSICS","start":"2026-03-30T02:20:00.000","end":"2026-03-30T06:20:00.000"},{"title":"Olimpiyat Yıldızları","start":"2026-03-30T06:20:00.000","end":"2026-03-30T06:35:00.000"},{"title":"YILDIZ'DA SÖYLEŞİ","start":"2026-03-30T06:35:00.000","end":"2026-03-30T06:55:00.000"},{"title":"KADRAJ","start":"2026-03-30T06:55:00.000","end":"2026-03-30T06:58:00.000"}]}